{
  "get": "fixtures/events",
  "parameters": {
    "fixture": "605429"
  },
  "errors": [],
  "results": 17,
  "paging": {
    "current": 1,
    "total": 1
  },
  "response": [
    {
      "time": {
        "elapsed": 7,
        "extra": null
      },
      "team": {
        "id": 726,
        "name": "Huesca",
        "logo": "https://media.api-sports.io/football/teams/726.png"
      },
      "player": {
        "id": 1291,
        "name": "D. Vavro"
      },
      "assist": {
        "id": 6084,
        "name": "G. Silva"
      },
      "type": "subst",
      "detail": "Substitution 1",
      "comments": null
    },
    {
      "time": {
        "elapsed": 17,
        "extra": null
      },
      "team": {
        "id": 726,
        "name": "Huesca",
        "logo": "https://media.api-sports.io/football/teams/726.png"
      },
      "player": {
        "id": 47287,
        "name": "Mikel Rico"
      },
      "assist": {
        "id": null,
        "name": null
      },
      "type": "Card",
      "detail": "Yellow Card",
      "comments": "Foul"
    },
    {
      "time": {
        "elapsed": 28,
        "extra": null
      },
      "team": {
        "id": 726,
        "name": "Huesca",
        "logo": "https://media.api-sports.io/football/teams/726.png"
      },
      "player": {
        "id": 47566,
        "name": "Javi Galán"
      },
      "assist": {
        "id": null,
        "name": null
      },
      "type": "Card",
      "detail": "Yellow Card",
      "comments": "Foul"
    },
    {
      "time": {
        "elapsed": 57,
        "extra": null
      },
      "team": {
        "id": 543,
        "name": "Real Betis",
        "logo": "https://media.api-sports.io/football/teams/543.png"
      },
      "player": {
        "id": 47348,
        "name": "Borja Iglesias"
      },
      "assist": {
        "id": null,
        "name": null
      },
      "type": "Goal",
      "detail": "Penalty",
      "comments": null
    },
    {
      "time": {
        "elapsed": 59,
        "extra": null
      },
      "team": {
        "id": 726,
        "name": "Huesca",
        "logo": "https://media.api-sports.io/football/teams/726.png"
      },
      "player": {
        "id": 47409,
        "name": "Dimitrios Siovas"
      },
      "assist": {
        "id": null,
        "name": null
      },
      "type": "Card",
      "detail": "Yellow Card",
      "comments": "Foul"
    },
    {
      "time": {
        "elapsed": 59,
        "extra": null
      },
      "team": {
        "id": 543,
        "name": "Real Betis",
        "logo": "https://media.api-sports.io/football/teams/543.png"
      },
      "player": {
        "id": 1579,
        "name": "Joaquín"
      },
      "assist": {
        "id": 1577,
        "name": "D. Lainez"
      },
      "type": "subst",
      "detail": "Substitution 1",
      "comments": null
    },
    {
      "time": {
        "elapsed": 61,
        "extra": null
      },
      "team": {
        "id": 726,
        "name": "Huesca",
        "logo": "https://media.api-sports.io/football/teams/726.png"
      },
      "player": {
        "id": 47566,
        "name": "Javier Galán"
      },
      "assist": {
        "id": 23,
        "name": "Sergio Gómez"
      },
      "type": "subst",
      "detail": "Substitution 2",
      "comments": null
    },
    {
      "time": {
        "elapsed": 61,
        "extra": null
      },
      "team": {
        "id": 726,
        "name": "Huesca",
        "logo": "https://media.api-sports.io/football/teams/726.png"
      },
      "player": {
        "id": 26302,
        "name": "Pablo Maffeo"
      },
      "assist": {
        "id": 47454,
        "name": "Pedro López"
      },
      "type": "subst",
      "detail": "Substitution 3",
      "comments": null
    },
    {
      "time": {
        "elapsed": 62,
        "extra": null
      },
      "team": {
        "id": 726,
        "name": "Huesca",
        "logo": "https://media.api-sports.io/football/teams/726.png"
      },
      "player": {
        "id": 47287,
        "name": "Mikel Rico"
      },
      "assist": {
        "id": 47179,
        "name": "Dani Escriche"
      },
      "type": "subst",
      "detail": "Substitution 4",
      "comments": null
    },
    {
      "time": {
        "elapsed": 68,
        "extra": null
      },
      "team": {
        "id": 726,
        "name": "Huesca",
        "logo": "https://media.api-sports.io/football/teams/726.png"
      },
      "player": {
        "id": 47324,
        "name": "Sandro Ramírez"
      },
      "assist": {
        "id": null,
        "name": null
      },
      "type": "Card",
      "detail": "Yellow Card",
      "comments": "Argument"
    },
    {
      "time": {
        "elapsed": 72,
        "extra": null
      },
      "team": {
        "id": 543,
        "name": "Real Betis",
        "logo": "https://media.api-sports.io/football/teams/543.png"
      },
      "player": {
        "id": 185477,
        "name": "Rodri"
      },
      "assist": {
        "id": 1586,
        "name": "Tello"
      },
      "type": "subst",
      "detail": "Substitution 2",
      "comments": null
    },
    {
      "time": {
        "elapsed": 80,
        "extra": null
      },
      "team": {
        "id": 726,
        "name": "Huesca",
        "logo": "https://media.api-sports.io/football/teams/726.png"
      },
      "player": {
        "id": 47409,
        "name": "D. Siovas"
      },
      "assist": {
        "id": 46805,
        "name": "Pedro Mosquera"
      },
      "type": "subst",
      "detail": "Substitution 5",
      "comments": null
    },
    {
      "time": {
        "elapsed": 83,
        "extra": null
      },
      "team": {
        "id": 543,
        "name": "Real Betis",
        "logo": "https://media.api-sports.io/football/teams/543.png"
      },
      "player": {
        "id": 47348,
        "name": "Borja Iglesias"
      },
      "assist": {
        "id": 1584,
        "name": "Loren Morón"
      },
      "type": "subst",
      "detail": "Substitution 3",
      "comments": null
    },
    {
      "time": {
        "elapsed": 83,
        "extra": null
      },
      "team": {
        "id": 543,
        "name": "Real Betis",
        "logo": "https://media.api-sports.io/football/teams/543.png"
      },
      "player": {
        "id": 1570,
        "name": "Sergio Canales"
      },
      "assist": {
        "id": 1573,
        "name": "A. Guardado"
      },
      "type": "subst",
      "detail": "Substitution 4",
      "comments": null
    },
    {
      "time": {
        "elapsed": 86,
        "extra": null
      },
      "team": {
        "id": 726,
        "name": "Huesca",
        "logo": "https://media.api-sports.io/football/teams/726.png"
      },
      "player": {
        "id": 47573,
        "name": "David Ferreiro"
      },
      "assist": {
        "id": null,
        "name": null
      },
      "type": "Card",
      "detail": "Yellow Card",
      "comments": "Argument"
    },
    {
      "time": {
        "elapsed": 88,
        "extra": null
      },
      "team": {
        "id": 543,
        "name": "Real Betis",
        "logo": "https://media.api-sports.io/football/teams/543.png"
      },
      "player": {
        "id": 1577,
        "name": "Diego Lainez"
      },
      "assist": {
        "id": null,
        "name": null
      },
      "type": "Card",
      "detail": "Yellow Card",
      "comments": "Foul"
    },
    {
      "time": {
        "elapsed": 90,
        "extra": null
      },
      "team": {
        "id": 726,
        "name": "Huesca",
        "logo": "https://media.api-sports.io/football/teams/726.png"
      },
      "player": {
        "id": 47179,
        "name": "Dani Escriche"
      },
      "assist": {
        "id": null,
        "name": null
      },
      "type": "Card",
      "detail": "Red Card",
      "comments": "Foul"
    }
  ]
}