{
  "get": "fixtures/events",
  "parameters": {
    "fixture": "608822"
  },
  "errors": [],
  "results": 22,
  "paging": {
    "current": 1,
    "total": 1
  },
  "response": [
    {
      "time": {
        "elapsed": 20,
        "extra": null
      },
      "team": {
        "id": 515,
        "name": "Spezia",
        "logo": "https://media.api-sports.io/football/teams/515.png"
      },
      "player": {
        "id": 38112,
        "name": "Julian Chabot"
      },
      "assist": {
        "id": null,
        "name": null
      },
      "type": "Card",
      "detail": "Yellow Card",
      "comments": "Foul"
    },
    {
      "time": {
        "elapsed": 30,
        "extra": null
      },
      "team": {
        "id": 487,
        "name": "Lazio",
        "logo": "https://media.api-sports.io/football/teams/487.png"
      },
      "player": {
        "id": 899,
        "name": "Andreas Pereira"
      },
      "assist": {
        "id": null,
        "name": null
      },
      "type": "Card",
      "detail": "Yellow Card",
      "comments": "Persistent fouling"
    },
    {
      "time": {
        "elapsed": 52,
        "extra": null
      },
      "team": {
        "id": 487,
        "name": "Lazio",
        "logo": "https://media.api-sports.io/football/teams/487.png"
      },
      "player": {
        "id": 899,
        "name": "Andreas Pereira"
      },
      "assist": {
        "id": 1859,
        "name": "Luis Alberto"
      },
      "type": "subst",
      "detail": "Substitution 1",
      "comments": null
    },
    {
      "time": {
        "elapsed": 52,
        "extra": null
      },
      "team": {
        "id": 487,
        "name": "Lazio",
        "logo": "https://media.api-sports.io/football/teams/487.png"
      },
      "player": {
        "id": 1855,
        "name": "S. Lulić"
      },
      "assist": {
        "id": 30859,
        "name": "M. Fares"
      },
      "type": "subst",
      "detail": "Substitution 2",
      "comments": null
    },
    {
      "time": {
        "elapsed": 56,
        "extra": null
      },
      "team": {
        "id": 487,
        "name": "Lazio",
        "logo": "https://media.api-sports.io/football/teams/487.png"
      },
      "player": {
        "id": 30866,
        "name": "M. Lazzari"
      },
      "assist": {
        "id": 1854,
        "name": "J. Correa"
      },
      "type": "Goal",
      "detail": "Normal Goal",
      "comments": null
    },
    {
      "time": {
        "elapsed": 65,
        "extra": null
      },
      "team": {
        "id": 515,
        "name": "Spezia",
        "logo": "https://media.api-sports.io/football/teams/515.png"
      },
      "player": {
        "id": 30836,
        "name": "G. Maggiore"
      },
      "assist": {
        "id": 21004,
        "name": "L. Agoume"
      },
      "type": "subst",
      "detail": "Substitution 1",
      "comments": null
    },
    {
      "time": {
        "elapsed": 65,
        "extra": null
      },
      "team": {
        "id": 515,
        "name": "Spezia",
        "logo": "https://media.api-sports.io/football/teams/515.png"
      },
      "player": {
        "id": 30687,
        "name": "S. Bastoni"
      },
      "assist": {
        "id": 30981,
        "name": "R. Marchizza"
      },
      "type": "subst",
      "detail": "Substitution 2",
      "comments": null
    },
    {
      "time": {
        "elapsed": 70,
        "extra": null
      },
      "team": {
        "id": 515,
        "name": "Spezia",
        "logo": "https://media.api-sports.io/football/teams/515.png"
      },
      "player": {
        "id": 31061,
        "name": "Diego Farias"
      },
      "assist": {
        "id": 47500,
        "name": "D. Verde"
      },
      "type": "subst",
      "detail": "Substitution 3",
      "comments": null
    },
    {
      "time": {
        "elapsed": 70,
        "extra": null
      },
      "team": {
        "id": 515,
        "name": "Spezia",
        "logo": "https://media.api-sports.io/football/teams/515.png"
      },
      "player": {
        "id": 10352,
        "name": "Léo Sena"
      },
      "assist": {
        "id": 13246,
        "name": "K. Agudelo"
      },
      "type": "subst",
      "detail": "Substitution 4",
      "comments": null
    },
    {
      "time": {
        "elapsed": 71,
        "extra": null
      },
      "team": {
        "id": 515,
        "name": "Spezia",
        "logo": "https://media.api-sports.io/football/teams/515.png"
      },
      "player": {
        "id": 30440,
        "name": "R. Piccoli"
      },
      "assist": {
        "id": 31318,
        "name": "M'Bala Nzola"
      },
      "type": "subst",
      "detail": "Substitution 5",
      "comments": null
    },
    {
      "time": {
        "elapsed": 72,
        "extra": null
      },
      "team": {
        "id": 487,
        "name": "Lazio",
        "logo": "https://media.api-sports.io/football/teams/487.png"
      },
      "player": {
        "id": 1856,
        "name": "S. Milinković-Savić"
      },
      "assist": {
        "id": 31678,
        "name": "J. Akpa Akpro"
      },
      "type": "subst",
      "detail": "Substitution 3",
      "comments": null
    },
    {
      "time": {
        "elapsed": 73,
        "extra": null
      },
      "team": {
        "id": 487,
        "name": "Lazio",
        "logo": "https://media.api-sports.io/football/teams/487.png"
      },
      "player": {
        "id": 1863,
        "name": "C. Immobile"
      },
      "assist": {
        "id": 1861,
        "name": "F. Caicedo"
      },
      "type": "subst",
      "detail": "Substitution 4",
      "comments": null
    },
    {
      "time": {
        "elapsed": 73,
        "extra": null
      },
      "team": {
        "id": 515,
        "name": "Spezia",
        "logo": "https://media.api-sports.io/football/teams/515.png"
      },
      "player": {
        "id": 47500,
        "name": "D. Verde"
      },
      "assist": {
        "id": 30845,
        "name": "E. Gyasi"
      },
      "type": "Goal",
      "detail": "Normal Goal",
      "comments": null
    },
    {
      "time": {
        "elapsed": 77,
        "extra": null
      },
      "team": {
        "id": 487,
        "name": "Lazio",
        "logo": "https://media.api-sports.io/football/teams/487.png"
      },
      "player": {
        "id": 1854,
        "name": "Joaquín Correa"
      },
      "assist": {
        "id": null,
        "name": null
      },
      "type": "Card",
      "detail": "Yellow Card",
      "comments": "Foul"
    },
    {
      "time": {
        "elapsed": 77,
        "extra": null
      },
      "team": {
        "id": 487,
        "name": "Lazio",
        "logo": "https://media.api-sports.io/football/teams/487.png"
      },
      "player": {
        "id": 1858,
        "name": "Lucas Leiva"
      },
      "assist": {
        "id": 1852,
        "name": "D. Cataldi"
      },
      "type": "subst",
      "detail": "Substitution 5",
      "comments": null
    },
    {
      "time": {
        "elapsed": 87,
        "extra": null
      },
      "team": {
        "id": 487,
        "name": "Lazio",
        "logo": "https://media.api-sports.io/football/teams/487.png"
      },
      "player": {
        "id": 1852,
        "name": "Danilo Cataldi"
      },
      "assist": {
        "id": null,
        "name": null
      },
      "type": "Var",
      "detail": "Goal cancelled",
      "comments": null
    },
    {
      "time": {
        "elapsed": 89,
        "extra": null
      },
      "team": {
        "id": 487,
        "name": "Lazio",
        "logo": "https://media.api-sports.io/football/teams/487.png"
      },
      "player": {
        "id": 1861,
        "name": "F. Caicedo"
      },
      "assist": {
        "id": null,
        "name": null
      },
      "type": "Goal",
      "detail": "Penalty",
      "comments": null
    },
    {
      "time": {
        "elapsed": 90,
        "extra": null
      },
      "team": {
        "id": 487,
        "name": "Lazio",
        "logo": "https://media.api-sports.io/football/teams/487.png"
      },
      "player": {
        "id": 1854,
        "name": "Joaquín Correa"
      },
      "assist": {
        "id": null,
        "name": null
      },
      "type": "Card",
      "detail": "Yellow Card",
      "comments": "Foul"
    },
    {
      "time": {
        "elapsed": 90,
        "extra": null
      },
      "team": {
        "id": 487,
        "name": "Lazio",
        "logo": "https://media.api-sports.io/football/teams/487.png"
      },
      "player": {
        "id": 1854,
        "name": "Joaquín Correa"
      },
      "assist": {
        "id": null,
        "name": null
      },
      "type": "Card",
      "detail": "Red Card",
      "comments": "Foul"
    },
    {
      "time": {
        "elapsed": 90,
        "extra": null
      },
      "team": {
        "id": 487,
        "name": "Lazio",
        "logo": "https://media.api-sports.io/football/teams/487.png"
      },
      "player": {
        "id": 30866,
        "name": "Manuel Lazzari"
      },
      "assist": {
        "id": null,
        "name": null
      },
      "type": "Card",
      "detail": "Red Card",
      "comments": "Violent conduct"
    },
    {
      "time": {
        "elapsed": 90,
        "extra": null
      },
      "team": {
        "id": 515,
        "name": "Spezia",
        "logo": "https://media.api-sports.io/football/teams/515.png"
      },
      "player": {
        "id": 13246,
        "name": "Kevin Agudelo"
      },
      "assist": {
        "id": null,
        "name": null
      },
      "type": "Card",
      "detail": "Yellow Card",
      "comments": "Argument"
    },
    {
      "time": {
        "elapsed": 90,
        "extra": null
      },
      "team": {
        "id": 515,
        "name": "Spezia",
        "logo": "https://media.api-sports.io/football/teams/515.png"
      },
      "player": {
        "id": 31318,
        "name": "M'Bala Nzola"
      },
      "assist": {
        "id": null,
        "name": null
      },
      "type": "Card",
      "detail": "Yellow Card",
      "comments": "Foul"
    }
  ]
}