{
  "get": "fixtures/events",
  "parameters": {
    "fixture": "587459"
  },
  "errors": [],
  "results": 13,
  "paging": {
    "current": 1,
    "total": 1
  },
  "response": [
    {
      "time": {
        "elapsed": 11,
        "extra": null
      },
      "team": {
        "id": 164,
        "name": "FSV Mainz 05",
        "logo": "https://media.api-sports.io/football/teams/164.png"
      },
      "player": {
        "id": 25928,
        "name": "K. Onisiwo"
      },
      "assist": {
        "id": 979,
        "name": "D. Kohr"
      },
      "type": "Goal",
      "detail": "Normal Goal",
      "comments": null
    },
    {
      "time": {
        "elapsed": 29,
        "extra": null
      },
      "team": {
        "id": 169,
        "name": "Eintracht Frankfurt",
        "logo": "https://media.api-sports.io/football/teams/169.png"
      },
      "player": {
        "id": 1822,
        "name": "S. Rode"
      },
      "assist": {
        "id": 38123,
        "name": "A. Hrustic"
      },
      "type": "subst",
      "detail": "Substitution 1",
      "comments": null
    },
    {
      "time": {
        "elapsed": 30,
        "extra": null
      },
      "team": {
        "id": 169,
        "name": "Eintracht Frankfurt",
        "logo": "https://media.api-sports.io/football/teams/169.png"
      },
      "player": {
        "id": 1821,
        "name": "Filip Kostić"
      },
      "assist": {
        "id": null,
        "name": null
      },
      "type": "Card",
      "detail": "Yellow Card",
      "comments": "Foul"
    },
    {
      "time": {
        "elapsed": 49,
        "extra": null
      },
      "team": {
        "id": 169,
        "name": "Eintracht Frankfurt",
        "logo": "https://media.api-sports.io/football/teams/169.png"
      },
      "player": {
        "id": 38123,
        "name": "Ajdin Hrustić"
      },
      "assist": {
        "id": null,
        "name": null
      },
      "type": "Card",
      "detail": "Yellow Card",
      "comments": "Foul"
    },
    {
      "time": {
        "elapsed": 56,
        "extra": null
      },
      "team": {
        "id": 164,
        "name": "FSV Mainz 05",
        "logo": "https://media.api-sports.io/football/teams/164.png"
      },
      "player": {
        "id": 2866,
        "name": "R. Quaison"
      },
      "assist": {
        "id": 25925,
        "name": "J. Boëtius"
      },
      "type": "subst",
      "detail": "Substitution 1",
      "comments": null
    },
    {
      "time": {
        "elapsed": 64,
        "extra": null
      },
      "team": {
        "id": 169,
        "name": "Eintracht Frankfurt",
        "logo": "https://media.api-sports.io/football/teams/169.png"
      },
      "player": {
        "id": 19040,
        "name": "E. Durm"
      },
      "assist": {
        "id": 1803,
        "name": "T. Chandler"
      },
      "type": "subst",
      "detail": "Substitution 2",
      "comments": null
    },
    {
      "time": {
        "elapsed": 64,
        "extra": null
      },
      "team": {
        "id": 169,
        "name": "Eintracht Frankfurt",
        "logo": "https://media.api-sports.io/football/teams/169.png"
      },
      "player": {
        "id": 957,
        "name": "D. Sow"
      },
      "assist": {
        "id": 1154,
        "name": "S. Ilsanker"
      },
      "type": "subst",
      "detail": "Substitution 3",
      "comments": null
    },
    {
      "time": {
        "elapsed": 65,
        "extra": null
      },
      "team": {
        "id": 169,
        "name": "Eintracht Frankfurt",
        "logo": "https://media.api-sports.io/football/teams/169.png"
      },
      "player": {
        "id": 1809,
        "name": "Tuta"
      },
      "assist": {
        "id": 335,
        "name": "A. Younes"
      },
      "type": "subst",
      "detail": "Substitution 4",
      "comments": null
    },
    {
      "time": {
        "elapsed": 71,
        "extra": null
      },
      "team": {
        "id": 169,
        "name": "Eintracht Frankfurt",
        "logo": "https://media.api-sports.io/football/teams/169.png"
      },
      "player": {
        "id": 2601,
        "name": "D. Kamada"
      },
      "assist": {
        "id": 2811,
        "name": "S. Zuber"
      },
      "type": "subst",
      "detail": "Substitution 5",
      "comments": null
    },
    {
      "time": {
        "elapsed": 77,
        "extra": null
      },
      "team": {
        "id": 164,
        "name": "FSV Mainz 05",
        "logo": "https://media.api-sports.io/football/teams/164.png"
      },
      "player": {
        "id": 25926,
        "name": "J. Burkardt"
      },
      "assist": {
        "id": 25922,
        "name": "L. Öztunali"
      },
      "type": "subst",
      "detail": "Substitution 2",
      "comments": null
    },
    {
      "time": {
        "elapsed": 78,
        "extra": null
      },
      "team": {
        "id": 164,
        "name": "FSV Mainz 05",
        "logo": "https://media.api-sports.io/football/teams/164.png"
      },
      "player": {
        "id": 25928,
        "name": "K. Onisiwo"
      },
      "assist": {
        "id": 24914,
        "name": "R. Glatzel"
      },
      "type": "subst",
      "detail": "Substitution 3",
      "comments": null
    },
    {
      "time": {
        "elapsed": 85,
        "extra": null
      },
      "team": {
        "id": 169,
        "name": "Eintracht Frankfurt",
        "logo": "https://media.api-sports.io/football/teams/169.png"
      },
      "player": {
        "id": 38123,
        "name": "A. Hrustic"
      },
      "assist": {
        "id": 2063,
        "name": "André Silva"
      },
      "type": "Goal",
      "detail": "Normal Goal",
      "comments": null
    },
    {
      "time": {
        "elapsed": 89,
        "extra": null
      },
      "team": {
        "id": 164,
        "name": "FSV Mainz 05",
        "logo": "https://media.api-sports.io/football/teams/164.png"
      },
      "player": {
        "id": 25918,
        "name": "L. Barreiro"
      },
      "assist": {
        "id": 25920,
        "name": "D. Latza"
      },
      "type": "subst",
      "detail": "Substitution 4",
      "comments": null
    }
  ]
}