{
  "get": "fixtures/events",
  "parameters": {
    "fixture": "592243"
  },
  "errors": [],
  "results": 7,
  "paging": {
    "current": 1,
    "total": 1
  },
  "response": [
    {
      "time": {
        "elapsed": 3,
        "extra": null
      },
      "team": {
        "id": 44,
        "name": "Burnley",
        "logo": "https://media.api-sports.io/football/teams/44.png"
      },
      "player": {
        "id": 18921,
        "name": "R. Brady"
      },
      "assist": {
        "id": 18926,
        "name": "A. Westwood"
      },
      "type": "Goal",
      "detail": "Normal Goal",
      "comments": null
    },
    {
      "time": {
        "elapsed": 29,
        "extra": null
      },
      "team": {
        "id": 45,
        "name": "Everton",
        "logo": "https://media.api-sports.io/football/teams/45.png"
      },
      "player": {
        "id": 630,
        "name": "F. Delph"
      },
      "assist": {
        "id": 18765,
        "name": "André Gomes"
      },
      "type": "subst",
      "detail": "Substitution 1",
      "comments": null
    },
    {
      "time": {
        "elapsed": 45,
        "extra": 3
      },
      "team": {
        "id": 45,
        "name": "Everton",
        "logo": "https://media.api-sports.io/football/teams/45.png"
      },
      "player": {
        "id": 18766,
        "name": "D. Calvert-Lewin"
      },
      "assist": {
        "id": 2413,
        "name": "Richarlison"
      },
      "type": "Goal",
      "detail": "Normal Goal",
      "comments": null
    },
    {
      "time": {
        "elapsed": 75,
        "extra": null
      },
      "team": {
        "id": 44,
        "name": "Burnley",
        "logo": "https://media.api-sports.io/football/teams/44.png"
      },
      "player": {
        "id": 19169,
        "name": "J. Rodriguez"
      },
      "assist": {
        "id": 18927,
        "name": "A. Barnes"
      },
      "type": "subst",
      "detail": "Substitution 1",
      "comments": null
    },
    {
      "time": {
        "elapsed": 81,
        "extra": null
      },
      "team": {
        "id": 45,
        "name": "Everton",
        "logo": "https://media.api-sports.io/football/teams/45.png"
      },
      "player": {
        "id": 18805,
        "name": "A. Doucouré"
      },
      "assist": {
        "id": 2795,
        "name": "G. Sigurðsson"
      },
      "type": "subst",
      "detail": "Substitution 2",
      "comments": null
    },
    {
      "time": {
        "elapsed": 86,
        "extra": null
      },
      "team": {
        "id": 44,
        "name": "Burnley",
        "logo": "https://media.api-sports.io/football/teams/44.png"
      },
      "player": {
        "id": 18921,
        "name": "R. Brady"
      },
      "assist": {
        "id": 18920,
        "name": "J. Benson"
      },
      "type": "subst",
      "detail": "Substitution 2",
      "comments": null
    },
    {
      "time": {
        "elapsed": 89,
        "extra": null
      },
      "team": {
        "id": 45,
        "name": "Everton",
        "logo": "https://media.api-sports.io/football/teams/45.png"
      },
      "player": {
        "id": 326,
        "name": "Allan"
      },
      "assist": {
        "id": 18768,
        "name": "C. Tosun"
      },
      "type": "subst",
      "detail": "Substitution 3",
      "comments": null
    }
  ]
}