{
  "get": "fixtures/events",
  "parameters": {
    "fixture": "587416"
  },
  "errors": [],
  "results": 17,
  "paging": {
    "current": 1,
    "total": 1
  },
  "response": [
    {
      "time": {
        "elapsed": 13,
        "extra": null
      },
      "team": {
        "id": 164,
        "name": "FSV Mainz 05",
        "logo": "https://media.api-sports.io/football/teams/164.png"
      },
      "player": {
        "id": 25907,
        "name": "Stefan Bell"
      },
      "assist": {
        "id": null,
        "name": null
      },
      "type": "Card",
      "detail": "Yellow Card",
      "comments": "Foul"
    },
    {
      "time": {
        "elapsed": 14,
        "extra": null
      },
      "team": {
        "id": 188,
        "name": "Arminia Bielefeld",
        "logo": "https://media.api-sports.io/football/teams/188.png"
      },
      "player": {
        "id": 25010,
        "name": "Anderson-Lenda Lucoqui"
      },
      "assist": {
        "id": null,
        "name": null
      },
      "type": "Card",
      "detail": "Yellow Card",
      "comments": "Foul"
    },
    {
      "time": {
        "elapsed": 56,
        "extra": null
      },
      "team": {
        "id": 164,
        "name": "FSV Mainz 05",
        "logo": "https://media.api-sports.io/football/teams/164.png"
      },
      "player": {
        "id": 25908,
        "name": "D. Brosinski"
      },
      "assist": {
        "id": null,
        "name": null
      },
      "type": "Goal",
      "detail": "Penalty",
      "comments": null
    },
    {
      "time": {
        "elapsed": 61,
        "extra": null
      },
      "team": {
        "id": 188,
        "name": "Arminia Bielefeld",
        "logo": "https://media.api-sports.io/football/teams/188.png"
      },
      "player": {
        "id": 25355,
        "name": "A. Maier"
      },
      "assist": {
        "id": 25499,
        "name": "F. Kunze"
      },
      "type": "subst",
      "detail": "Substitution 1",
      "comments": null
    },
    {
      "time": {
        "elapsed": 62,
        "extra": null
      },
      "team": {
        "id": 188,
        "name": "Arminia Bielefeld",
        "logo": "https://media.api-sports.io/football/teams/188.png"
      },
      "player": {
        "id": 36982,
        "name": "M. Vlap"
      },
      "assist": {
        "id": 2457,
        "name": "S. Córdova"
      },
      "type": "subst",
      "detail": "Substitution 2",
      "comments": null
    },
    {
      "time": {
        "elapsed": 69,
        "extra": null
      },
      "team": {
        "id": 164,
        "name": "FSV Mainz 05",
        "logo": "https://media.api-sports.io/football/teams/164.png"
      },
      "player": {
        "id": 24914,
        "name": "R. Glatzel"
      },
      "assist": {
        "id": 25928,
        "name": "K. Onisiwo"
      },
      "type": "subst",
      "detail": "Substitution 1",
      "comments": null
    },
    {
      "time": {
        "elapsed": 71,
        "extra": null
      },
      "team": {
        "id": 164,
        "name": "FSV Mainz 05",
        "logo": "https://media.api-sports.io/football/teams/164.png"
      },
      "player": {
        "id": 25908,
        "name": "D. Brosinski"
      },
      "assist": {
        "id": 1812,
        "name": "D. da Costa"
      },
      "type": "subst",
      "detail": "Substitution 2",
      "comments": null
    },
    {
      "time": {
        "elapsed": 71,
        "extra": null
      },
      "team": {
        "id": 164,
        "name": "FSV Mainz 05",
        "logo": "https://media.api-sports.io/football/teams/164.png"
      },
      "player": {
        "id": 25925,
        "name": "J. Boëtius"
      },
      "assist": {
        "id": 25920,
        "name": "D. Latza"
      },
      "type": "subst",
      "detail": "Substitution 3",
      "comments": null
    },
    {
      "time": {
        "elapsed": 71,
        "extra": null
      },
      "team": {
        "id": 188,
        "name": "Arminia Bielefeld",
        "logo": "https://media.api-sports.io/football/teams/188.png"
      },
      "player": {
        "id": 24968,
        "name": "M. Okugawa"
      },
      "assist": {
        "id": 25025,
        "name": "F. Klos"
      },
      "type": "subst",
      "detail": "Substitution 3",
      "comments": null
    },
    {
      "time": {
        "elapsed": 73,
        "extra": null
      },
      "team": {
        "id": 164,
        "name": "FSV Mainz 05",
        "logo": "https://media.api-sports.io/football/teams/164.png"
      },
      "player": {
        "id": 25920,
        "name": "Danny Latza"
      },
      "assist": {
        "id": null,
        "name": null
      },
      "type": "Card",
      "detail": "Yellow Card",
      "comments": "Foul"
    },
    {
      "time": {
        "elapsed": 76,
        "extra": null
      },
      "team": {
        "id": 188,
        "name": "Arminia Bielefeld",
        "logo": "https://media.api-sports.io/football/teams/188.png"
      },
      "player": {
        "id": 25030,
        "name": "A. Voglsammer"
      },
      "assist": {
        "id": null,
        "name": null
      },
      "type": "Goal",
      "detail": "Normal Goal",
      "comments": null
    },
    {
      "time": {
        "elapsed": 77,
        "extra": null
      },
      "team": {
        "id": 164,
        "name": "FSV Mainz 05",
        "logo": "https://media.api-sports.io/football/teams/164.png"
      },
      "player": {
        "id": 25926,
        "name": "J. Burkardt"
      },
      "assist": {
        "id": 729,
        "name": "Ádám Szalai"
      },
      "type": "subst",
      "detail": "Substitution 4",
      "comments": null
    },
    {
      "time": {
        "elapsed": 77,
        "extra": null
      },
      "team": {
        "id": 164,
        "name": "FSV Mainz 05",
        "logo": "https://media.api-sports.io/football/teams/164.png"
      },
      "player": {
        "id": 25907,
        "name": "S. Bell"
      },
      "assist": {
        "id": 25913,
        "name": "A. Hack"
      },
      "type": "subst",
      "detail": "Substitution 5",
      "comments": null
    },
    {
      "time": {
        "elapsed": 80,
        "extra": null
      },
      "team": {
        "id": 164,
        "name": "FSV Mainz 05",
        "logo": "https://media.api-sports.io/football/teams/164.png"
      },
      "player": {
        "id": 25918,
        "name": "Leandro Barreiro"
      },
      "assist": {
        "id": null,
        "name": null
      },
      "type": "Card",
      "detail": "Yellow Card",
      "comments": "Foul"
    },
    {
      "time": {
        "elapsed": 86,
        "extra": null
      },
      "team": {
        "id": 188,
        "name": "Arminia Bielefeld",
        "logo": "https://media.api-sports.io/football/teams/188.png"
      },
      "player": {
        "id": 25010,
        "name": "Anderson Lucoqui"
      },
      "assist": {
        "id": 8579,
        "name": "N. De Medina"
      },
      "type": "subst",
      "detail": "Substitution 4",
      "comments": null
    },
    {
      "time": {
        "elapsed": 86,
        "extra": null
      },
      "team": {
        "id": 188,
        "name": "Arminia Bielefeld",
        "logo": "https://media.api-sports.io/football/teams/188.png"
      },
      "player": {
        "id": 25030,
        "name": "A. Voglsammer"
      },
      "assist": {
        "id": 7682,
        "name": "C. Gebauer"
      },
      "type": "subst",
      "detail": "Substitution 5",
      "comments": null
    },
    {
      "time": {
        "elapsed": 90,
        "extra": null
      },
      "team": {
        "id": 164,
        "name": "FSV Mainz 05",
        "logo": "https://media.api-sports.io/football/teams/164.png"
      },
      "player": {
        "id": 25913,
        "name": "Alexander Hack"
      },
      "assist": {
        "id": null,
        "name": null
      },
      "type": "Card",
      "detail": "Yellow Card",
      "comments": "Foul"
    }
  ]
}