{
  "get": "fixtures/events",
  "parameters": {
    "fixture": "605078"
  },
  "errors": [],
  "results": 15,
  "paging": {
    "current": 1,
    "total": 1
  },
  "response": [
    {
      "time": {
        "elapsed": 7,
        "extra": null
      },
      "team": {
        "id": 715,
        "name": "Granada CF",
        "logo": "https://media.api-sports.io/football/teams/715.png"
      },
      "player": {
        "id": 1375,
        "name": "Soldado"
      },
      "assist": {
        "id": 2459,
        "name": "D. Machís"
      },
      "type": "Goal",
      "detail": "Normal Goal",
      "comments": null
    },
    {
      "time": {
        "elapsed": 22,
        "extra": null
      },
      "team": {
        "id": 542,
        "name": "Alaves",
        "logo": "https://media.api-sports.io/football/teams/542.png"
      },
      "player": {
        "id": 18907,
        "name": "Joselu"
      },
      "assist": {
        "id": null,
        "name": null
      },
      "type": "Goal",
      "detail": "Normal Goal",
      "comments": null
    },
    {
      "time": {
        "elapsed": 24,
        "extra": null
      },
      "team": {
        "id": 542,
        "name": "Alaves",
        "logo": "https://media.api-sports.io/football/teams/542.png"
      },
      "player": {
        "id": 35575,
        "name": "Edgar Mendez"
      },
      "assist": {
        "id": null,
        "name": null
      },
      "type": "Card",
      "detail": "Yellow Card",
      "comments": "Foul"
    },
    {
      "time": {
        "elapsed": 26,
        "extra": null
      },
      "team": {
        "id": 542,
        "name": "Alaves",
        "logo": "https://media.api-sports.io/football/teams/542.png"
      },
      "player": {
        "id": 1484,
        "name": "Rodrigo Battaglia"
      },
      "assist": {
        "id": null,
        "name": null
      },
      "type": "Card",
      "detail": "Yellow Card",
      "comments": "Foul"
    },
    {
      "time": {
        "elapsed": 46,
        "extra": null
      },
      "team": {
        "id": 542,
        "name": "Alaves",
        "logo": "https://media.api-sports.io/football/teams/542.png"
      },
      "player": {
        "id": 140834,
        "name": "A. Mahmoud"
      },
      "assist": {
        "id": 47355,
        "name": "Rubén Duarte"
      },
      "type": "subst",
      "detail": "Substitution 1",
      "comments": null
    },
    {
      "time": {
        "elapsed": 46,
        "extra": null
      },
      "team": {
        "id": 542,
        "name": "Alaves",
        "logo": "https://media.api-sports.io/football/teams/542.png"
      },
      "player": {
        "id": 47356,
        "name": "Rodrigo Ely"
      },
      "assist": {
        "id": 47360,
        "name": "Ximo Navarro"
      },
      "type": "subst",
      "detail": "Substitution 2",
      "comments": null
    },
    {
      "time": {
        "elapsed": 49,
        "extra": null
      },
      "team": {
        "id": 542,
        "name": "Alaves",
        "logo": "https://media.api-sports.io/football/teams/542.png"
      },
      "player": {
        "id": 18895,
        "name": "Florian Lejeune"
      },
      "assist": {
        "id": null,
        "name": null
      },
      "type": "Card",
      "detail": "Yellow Card",
      "comments": "Foul"
    },
    {
      "time": {
        "elapsed": 64,
        "extra": null
      },
      "team": {
        "id": 715,
        "name": "Granada CF",
        "logo": "https://media.api-sports.io/football/teams/715.png"
      },
      "player": {
        "id": 46689,
        "name": "Antonio Puertas"
      },
      "assist": {
        "id": 46687,
        "name": "Montoro"
      },
      "type": "subst",
      "detail": "Substitution 1",
      "comments": null
    },
    {
      "time": {
        "elapsed": 64,
        "extra": null
      },
      "team": {
        "id": 715,
        "name": "Granada CF",
        "logo": "https://media.api-sports.io/football/teams/715.png"
      },
      "player": {
        "id": 2449,
        "name": "Y. Herrera"
      },
      "assist": {
        "id": 18902,
        "name": "Kenedy"
      },
      "type": "subst",
      "detail": "Substitution 2",
      "comments": null
    },
    {
      "time": {
        "elapsed": 72,
        "extra": null
      },
      "team": {
        "id": 542,
        "name": "Alaves",
        "logo": "https://media.api-sports.io/football/teams/542.png"
      },
      "player": {
        "id": 46933,
        "name": "Luis Rioja"
      },
      "assist": {
        "id": 133453,
        "name": "Borja Sainz"
      },
      "type": "subst",
      "detail": "Substitution 3",
      "comments": null
    },
    {
      "time": {
        "elapsed": 79,
        "extra": null
      },
      "team": {
        "id": 715,
        "name": "Granada CF",
        "logo": "https://media.api-sports.io/football/teams/715.png"
      },
      "player": {
        "id": 2459,
        "name": "D. Machís"
      },
      "assist": {
        "id": null,
        "name": null
      },
      "type": "Goal",
      "detail": "Normal Goal",
      "comments": null
    },
    {
      "time": {
        "elapsed": 84,
        "extra": null
      },
      "team": {
        "id": 715,
        "name": "Granada CF",
        "logo": "https://media.api-sports.io/football/teams/715.png"
      },
      "player": {
        "id": 1375,
        "name": "Soldado"
      },
      "assist": {
        "id": 47265,
        "name": "Jorge Molina"
      },
      "type": "subst",
      "detail": "Substitution 3",
      "comments": null
    },
    {
      "time": {
        "elapsed": 84,
        "extra": null
      },
      "team": {
        "id": 715,
        "name": "Granada CF",
        "logo": "https://media.api-sports.io/football/teams/715.png"
      },
      "player": {
        "id": 2459,
        "name": "D. Machís"
      },
      "assist": {
        "id": 46683,
        "name": "Germán Sánchez"
      },
      "type": "subst",
      "detail": "Substitution 4",
      "comments": null
    },
    {
      "time": {
        "elapsed": 88,
        "extra": null
      },
      "team": {
        "id": 542,
        "name": "Alaves",
        "logo": "https://media.api-sports.io/football/teams/542.png"
      },
      "player": {
        "id": 35575,
        "name": "Edgar Méndez"
      },
      "assist": {
        "id": 47371,
        "name": "J. Guidetti"
      },
      "type": "subst",
      "detail": "Substitution 4",
      "comments": null
    },
    {
      "time": {
        "elapsed": 90,
        "extra": null
      },
      "team": {
        "id": 715,
        "name": "Granada CF",
        "logo": "https://media.api-sports.io/football/teams/715.png"
      },
      "player": {
        "id": 47085,
        "name": "Luis Milla"
      },
      "assist": {
        "id": 46677,
        "name": "Víctor Díaz"
      },
      "type": "subst",
      "detail": "Substitution 5",
      "comments": null
    }
  ]
}