{
  "get": "fixtures/events",
  "parameters": {
    "fixture": "587240"
  },
  "errors": [],
  "results": 15,
  "paging": {
    "current": 1,
    "total": 1
  },
  "response": [
    {
      "time": {
        "elapsed": 5,
        "extra": null
      },
      "team": {
        "id": 163,
        "name": "Borussia Monchengladbach",
        "logo": "https://media.api-sports.io/football/teams/163.png"
      },
      "player": {
        "id": 25638,
        "name": "F. Neuhaus"
      },
      "assist": {
        "id": null,
        "name": null
      },
      "type": "Goal",
      "detail": "Normal Goal",
      "comments": null
    },
    {
      "time": {
        "elapsed": 38,
        "extra": null
      },
      "team": {
        "id": 170,
        "name": "FC Augsburg",
        "logo": "https://media.api-sports.io/football/teams/170.png"
      },
      "player": {
        "id": 25300,
        "name": "Rani Khedira"
      },
      "assist": {
        "id": null,
        "name": null
      },
      "type": "Card",
      "detail": "Yellow Card",
      "comments": "Foul"
    },
    {
      "time": {
        "elapsed": 54,
        "extra": null
      },
      "team": {
        "id": 170,
        "name": "FC Augsburg",
        "logo": "https://media.api-sports.io/football/teams/170.png"
      },
      "player": {
        "id": 3001,
        "name": "R. Gumny"
      },
      "assist": {
        "id": 25288,
        "name": "R. Framberger"
      },
      "type": "subst",
      "detail": "Substitution 1",
      "comments": null
    },
    {
      "time": {
        "elapsed": 62,
        "extra": null
      },
      "team": {
        "id": 170,
        "name": "FC Augsburg",
        "logo": "https://media.api-sports.io/football/teams/170.png"
      },
      "player": {
        "id": 25288,
        "name": "Raphael Framberger"
      },
      "assist": {
        "id": null,
        "name": null
      },
      "type": "Card",
      "detail": "Yellow Card",
      "comments": "Foul"
    },
    {
      "time": {
        "elapsed": 65,
        "extra": null
      },
      "team": {
        "id": 170,
        "name": "FC Augsburg",
        "logo": "https://media.api-sports.io/football/teams/170.png"
      },
      "player": {
        "id": 25290,
        "name": "Jeffrey Gouweleeuw"
      },
      "assist": {
        "id": null,
        "name": null
      },
      "type": "Card",
      "detail": "Yellow Card",
      "comments": "Foul"
    },
    {
      "time": {
        "elapsed": 65,
        "extra": null
      },
      "team": {
        "id": 170,
        "name": "FC Augsburg",
        "logo": "https://media.api-sports.io/football/teams/170.png"
      },
      "player": {
        "id": 2797,
        "name": "A. Finnbogason"
      },
      "assist": {
        "id": 25298,
        "name": "A. Hahn"
      },
      "type": "subst",
      "detail": "Substitution 2",
      "comments": null
    },
    {
      "time": {
        "elapsed": 65,
        "extra": null
      },
      "team": {
        "id": 170,
        "name": "FC Augsburg",
        "logo": "https://media.api-sports.io/football/teams/170.png"
      },
      "player": {
        "id": 26257,
        "name": "F. Niederlechner"
      },
      "assist": {
        "id": 25297,
        "name": "M. Gregoritsch"
      },
      "type": "subst",
      "detail": "Substitution 3",
      "comments": null
    },
    {
      "time": {
        "elapsed": 66,
        "extra": null
      },
      "team": {
        "id": 170,
        "name": "FC Augsburg",
        "logo": "https://media.api-sports.io/football/teams/170.png"
      },
      "player": {
        "id": 25288,
        "name": "Raphael Framberger"
      },
      "assist": {
        "id": null,
        "name": null
      },
      "type": "Card",
      "detail": "Yellow Card",
      "comments": "Foul"
    },
    {
      "time": {
        "elapsed": 66,
        "extra": null
      },
      "team": {
        "id": 170,
        "name": "FC Augsburg",
        "logo": "https://media.api-sports.io/football/teams/170.png"
      },
      "player": {
        "id": 25288,
        "name": "Raphael Framberger"
      },
      "assist": {
        "id": null,
        "name": null
      },
      "type": "Card",
      "detail": "Red Card",
      "comments": "Foul"
    },
    {
      "time": {
        "elapsed": 67,
        "extra": null
      },
      "team": {
        "id": 163,
        "name": "Borussia Monchengladbach",
        "logo": "https://media.api-sports.io/football/teams/163.png"
      },
      "player": {
        "id": 25644,
        "name": "P. Herrmann"
      },
      "assist": {
        "id": 25353,
        "name": "V. Lazaro"
      },
      "type": "subst",
      "detail": "Substitution 1",
      "comments": null
    },
    {
      "time": {
        "elapsed": 78,
        "extra": null
      },
      "team": {
        "id": 163,
        "name": "Borussia Monchengladbach",
        "logo": "https://media.api-sports.io/football/teams/163.png"
      },
      "player": {
        "id": 25639,
        "name": "L. Stindl"
      },
      "assist": {
        "id": 21509,
        "name": "M. Thuram"
      },
      "type": "subst",
      "detail": "Substitution 2",
      "comments": null
    },
    {
      "time": {
        "elapsed": 81,
        "extra": null
      },
      "team": {
        "id": 170,
        "name": "FC Augsburg",
        "logo": "https://media.api-sports.io/football/teams/170.png"
      },
      "player": {
        "id": 48471,
        "name": "R. Vargas"
      },
      "assist": {
        "id": 25307,
        "name": "M. Richter"
      },
      "type": "subst",
      "detail": "Substitution 4",
      "comments": null
    },
    {
      "time": {
        "elapsed": 88,
        "extra": null
      },
      "team": {
        "id": 170,
        "name": "FC Augsburg",
        "logo": "https://media.api-sports.io/football/teams/170.png"
      },
      "player": {
        "id": 410,
        "name": "D. Caligiuri"
      },
      "assist": {
        "id": null,
        "name": null
      },
      "type": "Goal",
      "detail": "Normal Goal",
      "comments": null
    },
    {
      "time": {
        "elapsed": 89,
        "extra": null
      },
      "team": {
        "id": 163,
        "name": "Borussia Monchengladbach",
        "logo": "https://media.api-sports.io/football/teams/163.png"
      },
      "player": {
        "id": 25638,
        "name": "F. Neuhaus"
      },
      "assist": {
        "id": 2810,
        "name": "D. Zakaria"
      },
      "type": "subst",
      "detail": "Substitution 3",
      "comments": null
    },
    {
      "time": {
        "elapsed": 90,
        "extra": null
      },
      "team": {
        "id": 163,
        "name": "Borussia Monchengladbach",
        "logo": "https://media.api-sports.io/football/teams/163.png"
      },
      "player": {
        "id": 21509,
        "name": "Marcus Thuram"
      },
      "assist": {
        "id": null,
        "name": null
      },
      "type": "Card",
      "detail": "Yellow Card",
      "comments": "Foul"
    }
  ]
}